README.md
setup.py
darksky/__init__.py
darksky/api.py
darksky/base.py
darksky/forecast.py
darksky/utils.py
darksky/types/__init__.py
darksky/types/languages.py
darksky/types/units.py
darksky/types/weather.py
darksky_sdk_python.egg-info/PKG-INFO
darksky_sdk_python.egg-info/SOURCES.txt
darksky_sdk_python.egg-info/dependency_links.txt
darksky_sdk_python.egg-info/requires.txt
darksky_sdk_python.egg-info/top_level.txt
tests/__init__.py
tests/data.py
tests/mokcs.py
tests/test_base.py
tests/test_forecast.py
tests/utils.py