Metadata-Version: 1.1
Name: darksky-sdk-python
Version: 1.0.0
Summary: The Dark Sky API wrapper
Home-page: https://github.com/microparts/darksky-sdk-python
Author: Detrous
Author-email: detrous@protonmail.com
License: MIT License
Download-URL: https://github.com/microparts/darksky-sdk-python/archive/1.0.0.tar.gz
Platform: UNKNOWN
Classifier: Environment :: Web Environment
Classifier: Intended Audience :: Developers
Classifier: License :: OSI Approved :: MIT License
Classifier: Programming Language :: Python :: 3.6
Classifier: Topic :: Software Development :: Libraries :: Python Modules
